{
  "log_data_source_s3_bucket": "<ADD log_data S3 bucket name>",
  "log_data_source_s3_key": "<ADD log_data S3 key name>",
  "log_data_file_format": "<ADD log_data format (json | csv)>",
  "log_json_path":
    "<ADD log_data jsonpath file used in log_data COPY operation>",
  "song_data_source_s3_bucket": "<ADD log_data S3 key name>",
  "song_data_source_s3_key": "<ADD log_data S3 key name>",
  "song_data_file_format": "<ADD log_data format (json | csv)>",
  "log_data_target_staging_table": "<ADD table name for staging log_data>",
  "song_data_target_staging_table": "<ADD table name for staging song_data>",
  "songplays_target_table": "<ADD table name for songplays fact table>",
  "song_target_table": "<ADD table name for song dimension table>",
  "artist_target_table": "<ADD table name for artist dimension table>",
  "user_target_table": "<ADD table name for users dimension table>",
  "time_target_table": "<ADD table name for time dimension table>",
  "songplays_target_columns": "<ADD target columns for songplays table>",
  "user_target_columns": "<ADD target columns for user table>",
  "song_target_columns": "<ADD target columns for song table>",
  "artist_target_columns": "<ADD target columns for artist table>",
  "time_target_columns": "<ADD target columns for time table>",
  "songplays_insert_query": "<ADD data transfer SQL query for songplays table>",
  "songs_insert_query": "<ADD data transfer SQL query for songs table>",
  "artists_insert_query": "<ADD data transfer SQL query for artists table>",
  "users_insert_query": "<ADD data transfer SQL query for users table>",
  "time_insert_query": "<ADD data transfer SQL query for time table>",
  "data_quality_check_tables":
    "<ADD table names for which data check are run against>"
}
